<!DOCTYPE struts PUBLIC
    "-//Apache Software Foundation//DTD Struts Configuration 2.1.7//EN"
    "/xsd/struts-2.1.7.dtd">
<struts>
<package name="xmjck" extends="struts-default" namespace="/xmjck">
	<!-- 安保工程 -->
	<action name="selectTSDQ" class="jckwqgzController" method="selectTSDQ"/>
	<action name="selectTSDQ1" class="jckwqgzController" method="selectTSDQ1"/>
	<action name="insertAbgc" class="jckabgcController" method="insertAbgc"/>
	<action name="selectAbgc" class="jckabgcController" method="selectAbgc"/>
	<action name="selectAbgcById" class="jckabgcController" method="selectAbgcById"/>
	<action name="updateAbgcById" class="jckabgcController" method="updateAbgcById"/>
	<action name="deleteAbgcById" class="jckabgcController" method="deleteAbgcById	"/>
	<action name="xgJckAbgcShzt" class="jckabgcController" method="xgJckAbgcShzt"/>
	<action name="xgShzt2" class="jckabgcController" method="xgShzt2"/>
	
	<action name="xgJckAbgcSbzt" class="jckabgcController" method="xgJckAbgcSbzt"/>
	<action name="abgcGpsroad" class="jckabgcController" method="abgcGpsroad"/>
	<action name="selectJckRoad" class="jckabgcController" method="selectJckRoad"/>
	<action name="selectAbgcSh" class="jckabgcController" method="selectAbgcSh"/>
	<action name="xgJckAbgcTH" class="jckabgcController" method="xgJckAbgcTH"/>
	<action name="importAbgc" class="jckabgcController" method="importAbgc"/>
	<action name="exportExcel_abgc" class="jckabgcController" method="exportExcel_abgc"/>
	<action name="exportExcel_abgc_sh" class="jckabgcController" method="exportExcel_abgc_sh"/>
	<action name="onceAbgc" class="jckabgcController" method="onceAbgc"/>
	<action name="selAbgcCount" class="jckabgcController" method="selAbgcCount"/>
	<action name="selAbgcShCount" class="jckabgcController" method="selAbgcShCount"/>
	<!-- 危桥改造 -->
	<action name="insertWqgz" class="jckwqgzController" method="insertWqgz"/>
	<action name="selectWqgz" class="jckwqgzController" method="selectWqgz"/>
	<action name="selectWqgzById" class="jckwqgzController" method="selectWqgzById"/>
	<action name="updateWqgzById" class="jckwqgzController" method="updateWqgzById"/>
	<action name="deleteWqgzById" class="jckwqgzController" method="deleteWqgzById"/>
	<action name="xgJckWqgzShzt" class="jckwqgzController" method="xgJckWqgzShzt"/>
	<action name="xgJckWqgzSbzt" class="jckwqgzController" method="xgJckWqgzSbzt"/>
	<action name="wqgzGpsroad" class="jckwqgzController" method="wqgzGpsroad"/>
	<action name="wqgzGpsroad1" class="jckwqgzController" method="wqgzGpsroad1"/>
	<action name="JckWqgzRoad" class="jckwqgzController" method="JckWqgzRoad"/>
	<action name="selectJckShwqgz" class="jckwqgzController" method="selectJckShwqgz"/>
	<action name="xgJckWqgzTH" class="jckwqgzController" method="xgJckWqgzTH"/>
	<action name="importWqgz" class="jckwqgzController" method="importWqgz"/>
	<action name="exportExcel_wqgz" class="jckwqgzController" method="exportExcel_wqgz"/>
	<action name="exportExcel_wqgz_sh" class="jckwqgzController" method="exportExcel_wqgz_sh"/>
	<action name="onceWqgz" class="jckwqgzController" method="onceWqgz"/>
	<action name="selJsdj" class="jckwqgzController" method="selJsdj"/>
	<action name="selectWqgzCount" class="jckwqgzController" method="selectWqgzCount"/>
	<action name="selectWqgzCount1" class="jckwqgzController" method="selectWqgzCount1"/>
	<action name="selectWqgzShCount" class="jckwqgzController" method="selectWqgzShCount"/>
	<!-- 灾害防治 -->
	<action name="insertZhfz" class="jckzhfzController" method="insertZhfz"/>
	<action name="selectZhfz" class="jckzhfzController" method="selectZhfz"/>
	<action name="selectZhfzById" class="jckzhfzController" method="selectZhfzById"/>
	<action name="updateZhfzById" class="jckzhfzController" method="updateZhfzById"/>
	<action name="deleteZhfzById" class="jckzhfzController" method="deleteZhfzById"/>
	<action name="xgJckZhfzShzt" class="jckzhfzController" method="xgJckZhfzShzt"/>
	<action name="xgJckZhfzSbzt" class="jckzhfzController" method="xgJckZhfzSbzt"/>
	<action name="zhfzGpsroad" class="jckzhfzController" method="zhfzGpsroad"/>
	<action name="JckzhfzRoad" class="jckzhfzController" method="JckzhfzRoad"/>
	<action name="selectZhfzSh" class="jckzhfzController" method="selectZhfzSh"/>
	<action name="xgJckZhfzTH" class="jckzhfzController" method="xgJckZhfzTH"/>
	<action name="importZhfz" class="jckzhfzController" method="importZhfz"/>
	<action name="exportExcel_zhfz" class="jckzhfzController" method="exportExcel_zhfz"/>
	<action name="exportExcel_zhfz_sh" class="jckzhfzController" method="exportExcel_zhfz_sh"/>
	<action name="onceZhfz" class="jckzhfzController" method="onceZhfz"/>
	<action name="selZhfzCount" class="jckzhfzController" method="selZhfzCount"/>
	<action name="selZhfzShCount" class="jckzhfzController" method="selZhfzShCount"/>
 </package>
 <package name="xmsck" extends="struts-default" namespace="/xmsck">
 <!-- 危桥改造 -->
	<action name="insertSckwqgz" class="sckwqgzController" method="insertSckwqgz"/>
	<action name="selectSckwqgz" class="sckwqgzController" method="selectSckwqgz"/>
	<action name="deleteSckWqgz" class="sckwqgzController" method="deleteSckWqgz"/>
	<action name="updateSckwqgz" class="sckwqgzController" method="updateSckwqgz"/>
	<action name="selectSckwqgzById" class="sckwqgzController" method="selectSckwqgzById"/>
	<action name="xgSckWqgzSbzt" class="sckwqgzController" method="xgSckWqgzSbzt"/>
	<action name="xgSckWqgzTH" class="sckwqgzController" method="xgSckWqgzTH"/>
	<action name="selectSckShwqgz" class="sckwqgzController" method="selectSckShwqgz"/>
	<action name="xgSckWqgzShzt" class="sckwqgzController" method="xgSckWqgzShzt"/>
	<action name="onceSckWqgz" class="sckwqgzController" method="onceSckWqgz"/>
	<action name="bzWqgz" class="sckwqgzController" method="bzWqgz"/>
	<action name="exportExcel_wqgz_scgl" class="sckwqgzController" method="exportExcel_wqgz_scgl"/>
	<action name="exportExcel_wqgz_scsh" class="sckwqgzController" method="exportExcel_wqgz_scsh"/>
	<action name="importWqgz_sc" class="sckwqgzController" method="importWqgz_sc"/>
	<action name="lrjhSckwqgz" class="sckwqgzController" method="lrjhSckwqgz"/>
	<action name="selectWqgzCount" class="sckwqgzController" method="selectWqgzCount"/>
	<action name="selectWqgzShCount" class="sckwqgzController" method="selectWqgzShCount"/>
	<action name="lrjhWqgz" class="sckwqgzController" method="lrjhWqgz"/>
	<!-- 安保工程 -->
	<action name="insertSckabgc" class="sckabgcController" method="insertSckabgc"/>
	<action name="selectSckabgc" class="sckabgcController" method="selectSckabgc"/>
	<action name="deleteSckAbgc" class="sckabgcController" method="deleteSckAbgc"/>
	<action name="updateSckabgc" class="sckabgcController" method="updateSckabgc"/>
	<action name="selectSckabgcById" class="sckabgcController" method="selectSckabgcById"/>
	<action name="xgSckAbgcSbzt" class="sckabgcController" method="xgSckAbgcSbzt"/>
	<action name="selectSckShabgc" class="sckabgcController" method="selectSckShabgc"/>
	<action name="xgSckAbgcShzt" class="sckabgcController" method="xgSckAbgcShzt"/>
	<action name="xgSckAbgcTH" class="sckabgcController" method="xgSckAbgcTH"/>
	<action name="bzAbgc" class="sckabgcController" method="bzAbgc"/>
	<action name="onceSckAbgc" class="sckabgcController" method="onceSckAbgc"/>
	<action name="exportExcel_abgc_scgl" class="sckabgcController" method="exportExcel_abgc_scgl"/>
	<action name="exportExcel_abgc_scsh" class="sckabgcController" method="exportExcel_abgc_scsh"/>
	<action name="importAbgc_sc" class="sckabgcController" method="importAbgc_sc"/>
	<action name="lrjhSckabgc" class="sckabgcController" method="lrjhSckabgc"/>
	<action name="selSckAbgcCount" class="sckabgcController" method="selSckAbgcCount"/>
	<action name="selSckAbgcShCount" class="sckabgcController" method="selSckAbgcShCount"/>
	<action name="lrjhAbgc" class="sckabgcController" method="lrjhAbgc"/>
	<!-- 灾害防治 -->
	<action name="insertSckzhfz" class="sckzhfzController" method="insertSckzhfz"/>
	<action name="selectSckzhfz" class="sckzhfzController" method="selectSckzhfz"/>
	<action name="deleteSckZhfz" class="sckzhfzController" method="deleteSckZhfz"/>
	<action name="updateSckZhfz" class="sckzhfzController" method="updateSckZhfz"/>
	<action name="selectSckzhfzById" class="sckzhfzController" method="selectSckzhfzById"/>
	<action name="xgSckZhfzSbzt" class="sckzhfzController" method="xgSckZhfzSbzt"/>
	<action name="selectSckShzhfz" class="sckzhfzController" method="selectSckShzhfz"/>
	<action name="xgSckZhfzShzt" class="sckzhfzController" method="xgSckZhfzShzt"/>
	<action name="xgSckZhfzTH" class="sckzhfzController" method="xgSckZhfzTH"/>
	<action name="onceSckZhfz" class="sckzhfzController" method="onceSckZhfz"/>
	<action name="bzZhfz" class="sckzhfzController" method="bzZhfz"/>
	<action name="exportExcel_zhfz_scgl" class="sckzhfzController" method="exportExcel_zhfz_scgl"/>
	<action name="exportExcel_zhfz_scsh" class="sckzhfzController" method="exportExcel_zhfz_scsh"/>
	<action name="importZhfz_sc" class="sckzhfzController" method="importZhfz_sc"/>
	<action name="lrjhSckzhfz" class="sckzhfzController" method="lrjhSckzhfz"/>
	<action name="selSckZhfzCount" class="sckzhfzController" method="selSckZhfzCount"/>
	<action name="selSckZhfzShCount" class="sckzhfzController" method="selSckZhfzShCount"/>
	<action name="lrjhZhfz" class="sckzhfzController" method="lrjhZhfz"/>
 </package>
 <package name="zdycx" extends="struts-default" namespace="/zdycx">
	 <action name="selwqgzsjZdy" class="zdycxController" method="selwqgzsjZdy"/>
	 <action name="exportExcel_wqsjzdy" class="zdycxController" method="exportExcel_wqsjzdy"/>
	 <action name="selZdy" class="zdycxController" method="selZdy"/>
     <action name="exportExcel_zdy" class="zdycxController" method="exportExcel_zdy"/>
 </package>
 <package name="wqgzsj" extends="struts-default" namespace="/wqgzsj">
	 <action name="deleteqlzpbyxmbm" class="jckwqgzsjController" method="deleteqlzpbyxmbm"/>
  	 <action name="insertWqgz" class="jckwqgzsjController" method="insertWqgz"/>
 	 <action name="selectWqgz" class="jckwqgzsjController" method="selectWqgz"/>
 	 <action name="deleteWqgzsjById" class="jckwqgzsjController" method="deleteWqgzsjById"/>
 	 <action name="tuihuiWqgzsjById" class="jckwqgzsjController" method="tuihuiWqgzsjById"/>
 	 <action name="tuihuiWqgzsjsckById" class="jckwqgzsjController" method="tuihuiWqgzsjsckById"/>
 	 <action name="getwqgzZP" class="jckwqgzsjController" method="getwqgzZP"/>
 	 <action name="xgJckWqgzSbzt" class="jckwqgzsjController" method="xgJckWqgzSbzt"/>
 	 <action name="shtyWqgzsjById" class="jckwqgzsjController" method="shtyWqgzsjById"/>
 	 <action name="shbtyWqgzsjById" class="jckwqgzsjController" method="shbtyWqgzsjById"/>
 	 <action name="selectJckShwqgz" class="jckwqgzsjController" method="selectJckShwqgz"/>
 	 <action name="selectWqgzShCount" class="jckwqgzsjController" method="selectWqgzShCount"/>
 	 <action name="sjshtyWqgzsjById" class="jckwqgzsjController" method="sjshtyWqgzsjById"/>
 	 <action name="sjshbtyWqgzsjById" class="jckwqgzsjController" method="sjshbtyWqgzsjById"/>
 	 <action name="updateWqgz" class="jckwqgzsjController" method="updateWqgz"/>
 	 
 	 <action name="selectSckwqgz" class="jckwqgzsjController" method="selectSckwqgz"/>
 	 <action name="selectSckwqgzCount" class="jckwqgzsjController" method="selectSckwqgzCount"/>
 	 <action name="JckWqgzRoad" class="jckwqgzsjController" method="JckWqgzRoad"/>
 	 <action name="insertSckwqgz" class="jckwqgzsjController" method="insertSckwqgz"/>
 	 <action name="deleteSckWqgz" class="jckwqgzsjController" method="deleteSckWqgz"/>
 	 <action name="xgSckWqgzSbzt" class="jckwqgzsjController" method="xgSckWqgzSbzt"/>
 	 <action name="shtyWqgzsckById" class="jckwqgzsjController" method="shtyWqgzsckById"/>
 	 <action name="shbtyWqgzsckById" class="jckwqgzsjController" method="shbtyWqgzsckById"/>
 	 <action name="updateSckwqgz" class="jckwqgzsjController" method="updateSckwqgz"/>
 	 <action name="selectSckShwqgz" class="jckwqgzsjController" method="selectSckShwqgz"/>
 	 <action name="selectSckShwqgzCount" class="jckwqgzsjController" method="selectSckShwqgzCount"/>
 	 <action name="sjshtyWqgzsjwqgz" class="jckwqgzsjController" method="sjshtyWqgzsjwqgz"/>
 	 <action name="sjshbtyWqgzsjwqgz" class="jckwqgzsjController" method="sjshbtyWqgzsjwqgz"/>
 	 
 	 <action name="dcwqgzsjxmkExcel" class="jckwqgzsjController" method="dcwqgzsjxmkExcel"/>
 	 <action name="dcwqgzsjxmkshExcel" class="jckwqgzsjController" method="dcwqgzsjxmkshExcel"/>
 	 <action name="dcwqgzsjsckExcel" class="jckwqgzsjController" method="dcwqgzsjsckExcel"/>
 	 <action name="dcwqgzsjsckshExcel" class="jckwqgzsjController" method="dcwqgzsjsckshExcel"/>
 	 
 	 
 </package>
 <package name="aqsmfh" extends="struts-default" namespace="/aqsmfh">
 	<action name="selectXmkaqsmfhXMK" class="xmkaqsmfhController" method="selectXmkaqsmfhXMK"/>
 	<action name="loadXmkaqsmfhXMKCount" class="xmkaqsmfhController" method="loadXmkaqsmfhXMKCount"/>
 	<action name="smfhGpsroad" class="xmkaqsmfhController" method="smfhGpsroad"/>
 	<action name="insertAqsmfhxmk" class="xmkaqsmfhController" method="insertAqsmfhxmk"/>
 	<action name="xgXmkAFSbzt" class="xmkaqsmfhController" method="xgXmkAFSbzt"/>
 	<action name="updateAqsmfhxmk" class="xmkaqsmfhController" method="updateAqsmfhxmk"/>
 	<action name="deleteAfxmkById" class="xmkaqsmfhController" method="deleteAfxmkById"/>
 	
 	
 	
 	
 	<action name="selectSckaqsmfh" class="xmkaqsmfhController" method="selectSckaqsmfh"/>
 	<action name="loadSckaqsmfhCount" class="xmkaqsmfhController" method="loadSckaqsmfhCount"/>
 	<action name="aqsmfhJckGpsRoad" class="xmkaqsmfhController" method="aqsmfhJckGpsRoad"/>
 	<action name="insertAqsmfhsck" class="xmkaqsmfhController" method="insertAqsmfhsck"/>
 	<action name="selectafldList" class="xmkaqsmfhController" method="selectafldList"/>
 	<action name="selectAqsmfhsckbyid" class="xmkaqsmfhController" method="selectAqsmfhsckbyid"/>
 	<action name="selectAqsmfhxmkbyid" class="xmkaqsmfhController" method="selectAqsmfhxmkbyid"/>
 	<action name="updateAqsmfhsck" class="xmkaqsmfhController" method="updateAqsmfhsck"/>
 	<action name="selectSckaqsmfhld" class="xmkaqsmfhController" method="selectSckaqsmfhld"/>
 	<action name="insertAqsmfhsckld" class="xmkaqsmfhController" method="insertAqsmfhsckld"/>
 	<action name="loadscktjld" class="xmkaqsmfhController" method="loadscktjld"/>
 	<action name="delafldsck" class="xmkaqsmfhController" method="delafldsck"/>
 	<action name="deleteSckAf" class="xmkaqsmfhController" method="deleteSckAf"/>
 	<action name="sckAfSb" class="xmkaqsmfhController" method="sckAfSb"/>
 	<action name="afSckCs" class="xmkaqsmfhController" method="afSckCs"/>
 	
 </package>
</struts>
